Metadata-Version: 1.1
Name: django-sip-phonebook
Version: 1.0.15
Summary: Django based phonebook for Granstream telephones.
Home-page: https://github.com/shuckc/django-sip-phonebook
Author: Chris Shucksmith
Author-email: chris@shucksmith.co.uk
License: MIT
Platform: UNKNOWN
Classifier: Intended Audience :: Developers
Classifier: Topic :: Software Development
Classifier: License :: OSI Approved :: MIT License
Classifier: Programming Language :: Python :: 3
Classifier: Programming Language :: Python :: 3.2
Classifier: Programming Language :: Python :: 3.3
Classifier: Programming Language :: Python :: 3.4
